cml/__init__.py
cml/terminal.py
cml_easy-0.1.1.dist-info/LICENSE
cml_easy-0.1.1.dist-info/METADATA
cml_easy-0.1.1.dist-info/WHEEL
cml_easy-0.1.1.dist-info/top_level.txt
cml_easy-0.1.1.dist-info/RECORD
